[
  {
    "queue_len": 461.77,
    "len": 433,
    "inter_name": "杨高南路辅路与蓝村路路口",
    "lng": 121.533289,
    "lat": 31.211466
  },
  {
    "queue_len": 432.53,
    "len": 139,
    "inter_name": "元江路与嘉闵高架路入口路口",
    "lng": 121.389424,
    "lat": 31.045242
  },
  {
    "queue_len": 410.31,
    "len": 410,
    "inter_name": "东三里桥路与杨高南路路口",
    "lng": 121.525564,
    "lat": 31.192116
  },
  {
    "queue_len": 398.08,
    "len": 280,
    "inter_name": "两港大道与马五公路路口",
    "lng": 121.79721,
    "lat": 30.879027
  },
  {
    "queue_len": 395.74,
    "len": 364,
    "inter_name": "晋城路与沪太路路口",
    "lng": 121.424278,
    "lat": 31.280495
  },
  {
    "queue_len": 378.09,
    "len": 374,
    "inter_name": "曹安公路与华江公路路口",
    "lng": 121.346832,
    "lat": 31.25881
  },
  {
    "queue_len": 356.02,
    "len": 309,
    "inter_name": "沪太路与新沪路路口",
    "lng": 121.422793,
    "lat": 31.282958
  },
  {
    "queue_len": 355.27,
    "len": 335,
    "inter_name": "蟠龙路与龙联路路口",
    "lng": 121.278834,
    "lat": 31.190613
  },
  {
    "queue_len": 343.58,
    "len": 171,
    "inter_name": "武宁路与杨柳青路路口",
    "lng": 121.398817,
    "lat": 31.244688
  },
  {
    "queue_len": 309.44,
    "len": 266,
    "inter_name": "无名道路与黎康路路口",
    "lng": 121.365505,
    "lat": 31.130277
  },
  {
    "queue_len": 277.07,
    "len": 139,
    "inter_name": "元江路与嘉闵高架路入口路口",
    "lng": 121.389424,
    "lat": 31.045242
  },
  {
    "queue_len": 259.14,
    "len": 255,
    "inter_name": "汶水路与原平路路口",
    "lng": 121.431825,
    "lat": 31.289399
  },
  {
    "queue_len": 251.34,
    "len": 250,
    "inter_name": "大川公路交叉口",
    "lng": 121.735229,
    "lat": 31.058889
  },
  {
    "queue_len": 246.83,
    "len": 209,
    "inter_name": "莲花南路与罗秀路路口",
    "lng": 121.406332,
    "lat": 31.127273
  },
  {
    "queue_len": 223.87,
    "len": 215,
    "inter_name": "武宁路与大渡河路路口",
    "lng": 121.396941,
    "lat": 31.24485
  },
  {
    "queue_len": 220.69,
    "len": 217,
    "inter_name": "Ｇ５０沪渝高速出口与Ｇ５０沪渝高速入口路口",
    "lng": 121.125921,
    "lat": 31.130986
  },
  {
    "queue_len": 217.63,
    "len": 214,
    "inter_name": "龙东大道与科苑路路口",
    "lng": 121.586994,
    "lat": 31.212557
  },
  {
    "queue_len": 213.33,
    "len": 203,
    "inter_name": "金沙江路与泾阳路路口",
    "lng": 121.364825,
    "lat": 31.238992
  },
  {
    "queue_len": 210.34,
    "len": 198,
    "inter_name": "莲花路与莲花（南）路路口",
    "lng": 121.404297,
    "lat": 31.133613
  },
  {
    "queue_len": 198.09,
    "len": 191,
    "inter_name": "复兴东路与中山南路路口",
    "lng": 121.503116,
    "lat": 31.222348
  },
  {
    "queue_len": 197.86,
    "len": 187,
    "inter_name": "广灵四路与新市路路口",
    "lng": 121.480792,
    "lat": 31.286
  },
  {
    "queue_len": 191.68,
    "len": 190,
    "inter_name": "世纪大道与陆家嘴环路路口",
    "lng": 121.50911,
    "lat": 31.235192
  },
  {
    "queue_len": 190.87,
    "len": 119,
    "inter_name": "淮海中路与西藏南路路口",
    "lng": 121.480325,
    "lat": 31.225653
  },
  {
    "queue_len": 187.2,
    "len": 176,
    "inter_name": "虹许路与延安西路路口",
    "lng": 121.388366,
    "lat": 31.194466
  },
  {
    "queue_len": 180.12,
    "len": 176,
    "inter_name": "虹许路与延安西路路口",
    "lng": 121.388366,
    "lat": 31.194466
  },
  {
    "queue_len": 174.49,
    "len": 166,
    "inter_name": "虹许路与延安西路路口",
    "lng": 121.388366,
    "lat": 31.194466
  },
  {
    "queue_len": 165.79,
    "len": 157,
    "inter_name": "南辅路与闵松路路口",
    "lng": 121.373394,
    "lat": 31.117947
  },
  {
    "queue_len": 159.95,
    "len": 157,
    "inter_name": "南奉公路交叉口",
    "lng": 121.507498,
    "lat": 30.919886
  },
  {
    "queue_len": 158.58,
    "len": 157,
    "inter_name": "乳山路与东方路路口",
    "lng": 121.52214,
    "lat": 31.235547
  },
  {
    "queue_len": 153.53,
    "len": 143,
    "inter_name": "江川东路与永平南路路口",
    "lng": 121.434108,
    "lat": 31.01052
  },
  {
    "queue_len": 153.44,
    "len": 152,
    "inter_name": "长宁路与中山西路路口",
    "lng": 121.410837,
    "lat": 31.21719
  },
  {
    "queue_len": 153.38,
    "len": 150,
    "inter_name": "虹梅南路与放鹤路路口",
    "lng": 121.452487,
    "lat": 31.047628
  },
  {
    "queue_len": 149.92,
    "len": 149,
    "inter_name": "东陆公路与杨高北路路口",
    "lng": 121.604286,
    "lat": 31.266503
  },
  {
    "queue_len": 148.13,
    "len": 142,
    "inter_name": "金科路与华夏中路路口",
    "lng": 121.602443,
    "lat": 31.173773
  },
  {
    "queue_len": 147.41,
    "len": 124,
    "inter_name": "西藏中路与新闸路路口",
    "lng": 121.473481,
    "lat": 31.237702
  },
  {
    "queue_len": 147.24,
    "len": 114,
    "inter_name": "金陵东路与金陵中路路口",
    "lng": 121.479694,
    "lat": 31.226621
  },
  {
    "queue_len": 146.6,
    "len": 119,
    "inter_name": "淮海中路与西藏南路路口",
    "lng": 121.480325,
    "lat": 31.225653
  },
  {
    "queue_len": 146.2,
    "len": 144,
    "inter_name": "汶水东路与凉城路路口",
    "lng": 121.4711,
    "lat": 31.29126
  },
  {
    "queue_len": 141.81,
    "len": 131,
    "inter_name": "天目西路与恒丰路路口",
    "lng": 121.45369,
    "lat": 31.245832
  },
  {
    "queue_len": 137.13,
    "len": 135,
    "inter_name": "共和新路与延长路路口",
    "lng": 121.45557,
    "lat": 31.271463
  },
  {
    "queue_len": 135.02,
    "len": 119,
    "inter_name": "中环路出口与申江路路口",
    "lng": 121.625053,
    "lat": 31.200622
  },
  {
    "queue_len": 134.62,
    "len": 115,
    "inter_name": "武宁路与内环高架路出口路口",
    "lng": 121.419391,
    "lat": 31.24166
  },
  {
    "queue_len": 134.18,
    "len": 67,
    "inter_name": "华山路与泰安路路口",
    "lng": 121.433839,
    "lat": 31.204942
  },
  {
    "queue_len": 129.58,
    "len": 128,
    "inter_name": "长江西路与康宁路路口",
    "lng": 121.427622,
    "lat": 31.327182
  },
  {
    "queue_len": 123.58,
    "len": 27,
    "inter_name": "南辅路与闵松路路口",
    "lng": 121.373394,
    "lat": 31.117947
  },
  {
    "queue_len": 122.67,
    "len": 119,
    "inter_name": "邯郸路与国定路路口",
    "lng": 121.508843,
    "lat": 31.298005
  },
  {
    "queue_len": 119.86,
    "len": 106,
    "inter_name": "鲁班路与南塘浜路路口",
    "lng": 121.474864,
    "lat": 31.203962
  },
  {
    "queue_len": 118.41,
    "len": 114,
    "inter_name": "曲阳路与大连西路路口",
    "lng": 121.490493,
    "lat": 31.276504
  },
  {
    "queue_len": 117.04,
    "len": 104,
    "inter_name": "东方路与龙阳路路口",
    "lng": 121.52185,
    "lat": 31.200595
  },
  {
    "queue_len": 115.84,
    "len": 106,
    "inter_name": "西藏中路与九江路路口",
    "lng": 121.474947,
    "lat": 31.233755
  },
  {
    "queue_len": 115.25,
    "len": 107,
    "inter_name": "金门路与河南南路路口",
    "lng": 121.487166,
    "lat": 31.228861
  },
  {
    "queue_len": 113.47,
    "len": 108,
    "inter_name": "玉屏南路与天山支路路口",
    "lng": 121.399482,
    "lat": 31.215145
  },
  {
    "queue_len": 113.44,
    "len": 108,
    "inter_name": "中山北路与光新路路口",
    "lng": 121.432892,
    "lat": 31.250238
  },
  {
    "queue_len": 110.43,
    "len": 100,
    "inter_name": "石龙路与永川路路口",
    "lng": 121.439094,
    "lat": 31.155606
  },
  {
    "queue_len": 110.35,
    "len": 98,
    "inter_name": "杨思路与杨思西路路口",
    "lng": 121.484261,
    "lat": 31.156373
  },
  {
    "queue_len": 109.58,
    "len": 85,
    "inter_name": "祁连山南路与绥德路路口",
    "lng": 121.376313,
    "lat": 31.264918
  },
  {
    "queue_len": 107.57,
    "len": 27,
    "inter_name": "南辅路与闵松路路口",
    "lng": 121.373394,
    "lat": 31.117947
  },
  {
    "queue_len": 106.31,
    "len": 100,
    "inter_name": "延安中路与茂名南路路口",
    "lng": 121.460815,
    "lat": 31.223948
  },
  {
    "queue_len": 105.26,
    "len": 52,
    "inter_name": "中山东路与华扩路路口",
    "lng": 121.266304,
    "lat": 31.011518
  },
  {
    "queue_len": 103.38,
    "len": 85,
    "inter_name": "沪青平公路与七莘路路口",
    "lng": 121.337798,
    "lat": 31.171386
  },
  {
    "queue_len": 100.06,
    "len": 79,
    "inter_name": "高科中路与罗山高架路入口路口",
    "lng": 121.578595,
    "lat": 31.193121
  },
  {
    "queue_len": 99.94,
    "len": 95,
    "inter_name": "共和新路与共江路路口",
    "lng": 121.443437,
    "lat": 31.327124
  },
  {
    "queue_len": 96.37,
    "len": 93,
    "inter_name": "明中西路与明中路路口",
    "lng": 121.316166,
    "lat": 31.072848
  },
  {
    "queue_len": 95.77,
    "len": 94,
    "inter_name": "龙东大道与金桥路路口",
    "lng": 121.608526,
    "lat": 31.219762
  },
  {
    "queue_len": 95.22,
    "len": 85,
    "inter_name": "沪青平公路与七莘路路口",
    "lng": 121.337798,
    "lat": 31.171386
  },
  {
    "queue_len": 93.84,
    "len": 85,
    "inter_name": "共和新路与临汾路路口",
    "lng": 121.448623,
    "lat": 31.310712
  },
  {
    "queue_len": 93.33,
    "len": 73,
    "inter_name": "延安东路与浙江南路路口",
    "lng": 121.481511,
    "lat": 31.230289
  },
  {
    "queue_len": 93.18,
    "len": 84,
    "inter_name": "广中路与水电路路口",
    "lng": 121.475234,
    "lat": 31.277719
  },
  {
    "queue_len": 93.18,
    "len": 56,
    "inter_name": "宝山路与宝昌路路口",
    "lng": 121.477103,
    "lat": 31.25597
  },
  {
    "queue_len": 90.01,
    "len": 86,
    "inter_name": "孙桥路与张江路路口",
    "lng": 121.630456,
    "lat": 31.186342
  },
  {
    "queue_len": 88.97,
    "len": 79,
    "inter_name": "中春路与沪松公路路口",
    "lng": 121.339933,
    "lat": 31.150065
  },
  {
    "queue_len": 88.9,
    "len": 86,
    "inter_name": "华夏西路与耀龙路路口",
    "lng": 121.475946,
    "lat": 31.146128
  },
  {
    "queue_len": 88.03,
    "len": 86,
    "inter_name": "宛平南路与宛平路路口",
    "lng": 121.44476,
    "lat": 31.197179
  },
  {
    "queue_len": 87.38,
    "len": 83,
    "inter_name": "延安西路与Ｇ５０沪渝高速辅路路口",
    "lng": 121.358173,
    "lat": 31.183201
  },
  {
    "queue_len": 86.67,
    "len": 76,
    "inter_name": "内环高架路出口与中山北二路路口",
    "lng": 121.522081,
    "lat": 31.285721
  },
  {
    "queue_len": 85.82,
    "len": 83,
    "inter_name": "天山路与泸定路桥路口",
    "lng": 121.385401,
    "lat": 31.215275
  },
  {
    "queue_len": 85.54,
    "len": 82,
    "inter_name": "水清路与水清南路路口",
    "lng": 121.382689,
    "lat": 31.113138
  },
  {
    "queue_len": 84.34,
    "len": 84,
    "inter_name": "金沙江路与宁夏路路口",
    "lng": 121.410548,
    "lat": 31.231165
  },
  {
    "queue_len": 84.15,
    "len": 77,
    "inter_name": "汶水路与真北路路口",
    "lng": 121.405184,
    "lat": 31.287285
  },
  {
    "queue_len": 81.66,
    "len": 64,
    "inter_name": "银都路与老沪闵路路口",
    "lng": 121.423395,
    "lat": 31.100994
  },
  {
    "queue_len": 79.7,
    "len": 63,
    "inter_name": "淮海中路与南北高架路入口路口",
    "lng": 121.471374,
    "lat": 31.221894
  },
  {
    "queue_len": 79.24,
    "len": 70,
    "inter_name": "西藏南路与陆家浜路路口",
    "lng": 121.486045,
    "lat": 31.211819
  },
  {
    "queue_len": 76.81,
    "len": 76,
    "inter_name": "凯旋路与虹桥路路口",
    "lng": 121.422162,
    "lat": 31.195439
  },
  {
    "queue_len": 76.51,
    "len": 17,
    "inter_name": "金建路与大叶公路路口",
    "lng": 121.510298,
    "lat": 30.976424
  },
  {
    "queue_len": 75.84,
    "len": 62,
    "inter_name": "万源路与无名道路路口",
    "lng": 121.400547,
    "lat": 31.130028
  },
  {
    "queue_len": 72.28,
    "len": 64,
    "inter_name": "瑞金一路与长乐路路口",
    "lng": 121.4633,
    "lat": 31.22133
  },
  {
    "queue_len": 70.19,
    "len": 66,
    "inter_name": "沪宜公路与众仁路路口",
    "lng": 121.32172,
    "lat": 31.294287
  },
  {
    "queue_len": 68.38,
    "len": 62,
    "inter_name": "虹梅南路与无名道路路口",
    "lng": 121.420254,
    "lat": 31.129008
  },
  {
    "queue_len": 65.44,
    "len": 57,
    "inter_name": "龙阳路与沪南路路口",
    "lng": 121.547097,
    "lat": 31.199758
  },
  {
    "queue_len": 65.4,
    "len": 62,
    "inter_name": "天潼路与峨嵋路路口",
    "lng": 121.490697,
    "lat": 31.245865
  },
  {
    "queue_len": 65.3,
    "len": 59,
    "inter_name": "华夏西路与沪南路路口",
    "lng": 121.563269,
    "lat": 31.162871
  },
  {
    "queue_len": 64.25,
    "len": 63,
    "inter_name": "延安西路与种德桥路路口",
    "lng": 121.42033,
    "lat": 31.209037
  },
  {
    "queue_len": 63.29,
    "len": 63,
    "inter_name": "淮海中路与南北高架路入口路口",
    "lng": 121.471374,
    "lat": 31.221894
  },
  {
    "queue_len": 62.97,
    "len": 61,
    "inter_name": "中山南路与陆家浜路路口",
    "lng": 121.501455,
    "lat": 31.209429
  },
  {
    "queue_len": 60.46,
    "len": 55,
    "inter_name": "新闸路与南北高架路入口路口",
    "lng": 121.464252,
    "lat": 31.238321
  },
  {
    "queue_len": 56.61,
    "len": 53,
    "inter_name": "中山北路与光新路路口",
    "lng": 121.432892,
    "lat": 31.250238
  },
  {
    "queue_len": 56.19,
    "len": 51,
    "inter_name": "中山南路与陆家浜路路口",
    "lng": 121.501455,
    "lat": 31.209429
  },
  {
    "queue_len": 53.7,
    "len": 45,
    "inter_name": "海宁路与吴淞路路口",
    "lng": 121.488675,
    "lat": 31.25192
  },
  {
    "queue_len": 51.3,
    "len": 50,
    "inter_name": "长宁路与凯旋路路口",
    "lng": 121.416048,
    "lat": 31.218042
  },
  {
    "queue_len": 51.04,
    "len": 51,
    "inter_name": "中山南一路与制造局路路口",
    "lng": 121.485644,
    "lat": 31.200103
  },
  {
    "queue_len": 51.02,
    "len": 49,
    "inter_name": "四平路与贯中路路口",
    "lng": 121.489949,
    "lat": 31.262311
  },
  {
    "queue_len": 50.99,
    "len": 47,
    "inter_name": "长宁路与凯旋路路口",
    "lng": 121.416048,
    "lat": 31.218042
  },
  {
    "queue_len": 47.48,
    "len": 46,
    "inter_name": "北京西路与南北高架路入口路口",
    "lng": 121.466202,
    "lat": 31.234682
  },
  {
    "queue_len": 47.36,
    "len": 45,
    "inter_name": "延安东路与中山东二路路口",
    "lng": 121.491915,
    "lat": 31.233208
  },
  {
    "queue_len": 47.15,
    "len": 22,
    "inter_name": "崧泽大道与诸光路路口",
    "lng": 121.294419,
    "lat": 31.192635
  },
  {
    "queue_len": 47.13,
    "len": 43,
    "inter_name": "东三里桥路与杨高南路路口",
    "lng": 121.525564,
    "lat": 31.192116
  },
  {
    "queue_len": 44.25,
    "len": 42,
    "inter_name": "花木路与芳甸路路口",
    "lng": 121.561646,
    "lat": 31.213575
  },
  {
    "queue_len": 40.12,
    "len": 38,
    "inter_name": "武胜路与威海路路口",
    "lng": 121.469529,
    "lat": 31.227677
  },
  {
    "queue_len": 35.32,
    "len": 22,
    "inter_name": "崧泽大道与诸光路路口",
    "lng": 121.294419,
    "lat": 31.192635
  },
  {
    "queue_len": 33.75,
    "len": 25,
    "inter_name": "申迪西路与无名道路路口",
    "lng": 121.66619,
    "lat": 31.133803
  },
  {
    "queue_len": 26.67,
    "len": 22,
    "inter_name": "延安中路与华山路路口",
    "lng": 121.445626,
    "lat": 31.220965
  },
  {
    "queue_len": 25.31,
    "len": 21,
    "inter_name": "卫五北路与沪杭公路路口",
    "lng": 121.307723,
    "lat": 30.713877
  },
  {
    "queue_len": 22.11,
    "len": 22,
    "inter_name": "延安中路与华山路路口",
    "lng": 121.445626,
    "lat": 31.220965
  }
]